pyprinttags.py
taglib.cpython-310-darwin.so
pytaglib-3.1.0.dist-info/RECORD
pytaglib-3.1.0.dist-info/WHEEL
pytaglib-3.1.0.dist-info/entry_points.txt
pytaglib-3.1.0.dist-info/top_level.txt
pytaglib-3.1.0.dist-info/METADATA
pytaglib-3.1.0.dist-info/licenses/LICENSE.txt
