Metadata-Version: 2.4
Name: pytaglib
Version: 3.1.0
Summary: cross-platform, Python audio metadata ("tagging") library based on TagLib
Author-email: Michael Helmling <michaelhelmling@posteo.de>
License-Expression: GPL-3.0-or-later
Project-URL: Repository, https://github.com/supermihi/pytaglib
Project-URL: Issues, https://github.com/supermihi/pytaglib/issues
Project-URL: Changelog, https://github.com/supermihi/pytaglib/blob/main/CHANGELOG.md
Classifier: Development Status :: 5 - Production/Stable
Classifier: Intended Audience :: Developers
Classifier: Natural Language :: English
Classifier: Operating System :: OS Independent
Classifier: Programming Language :: Cython
Classifier: Programming Language :: Python
Classifier: Programming Language :: Python :: 3
Classifier: Topic :: Software Development :: Libraries :: Python Modules
Requires-Python: >=3.9
License-File: LICENSE.txt
Provides-Extra: tests
Requires-Dist: pytest<8.5.0,>=8.1.1; extra == "tests"
Dynamic: license-file
